libdb/__init__.py
libdb/db_manager.py
tests/__init__.py
tests/test_db_manager.py
libdb-4.6.0.dist-info/LICENSE
libdb-4.6.0.dist-info/METADATA
libdb-4.6.0.dist-info/WHEEL
libdb-4.6.0.dist-info/top_level.txt
libdb-4.6.0.dist-info/RECORD
