Metadata-Version: 2.1
Name: libdb
Version: 4.6.0
Summary: Easy Management and Creation of Database Based on JSON Format with High Speed and Optimized
Home-page: https://github.com/libdb/libdb
Author: Mmdrza
Author-email: Pymmdrza@gmail.com
License: MIT
Classifier: Programming Language :: Python :: 3
Classifier: License :: OSI Approved :: MIT License
Classifier: Operating System :: OS Independent
Requires-Python: >=3.6
License-File: LICENSE
